openmc_plot/__init__.py
openmc_plot/_version.py
openmc_plot/app.py
openmc_plot/cross_sections.xml
openmc_plot/launch.py
openmc_plot/utils.py
openmc_plot/pages/1_🖼_Geometry_plot.py
openmc_plot/pages/2_🧊_Regular_mesh_plot.py
openmc_plot/pages/3_✴️_Source_plot.py
openmc_plot/pages/4_🪟_Weight_window_plot.py
openmc_plot/pages/5_🍕_DAGMC_slice_plot.py
openmc_plot/pages/6_☢_Depletion_plot.py
openmc_plot/pages/7_🛢️_Cylindrical_mesh_plot.py
openmc_plot/pages/dagmc.h5m
openmc_plot-0.3.3.dist-info/LICENSE
openmc_plot-0.3.3.dist-info/METADATA
openmc_plot-0.3.3.dist-info/WHEEL
openmc_plot-0.3.3.dist-info/entry_points.txt
openmc_plot-0.3.3.dist-info/top_level.txt
openmc_plot-0.3.3.dist-info/RECORD
