Metadata-Version: 2.1
Name: openmc_plot
Version: 0.3.3
Summary: A Python package containing a collection of scripts for producing and downloading data for OpenMC
Author-email: Jonathan Shimwell <mail@jshimwell.com>
License: MIT License
Project-URL: Homepage, https://github.com/fusion-energy/openmc_plot
Project-URL: Bug Tracker, https://github.com/fusion-energy/openmc_plot/issues
Keywords: openmc,plot
Classifier: Programming Language :: Python :: 3
Classifier: License :: OSI Approved :: MIT License
Classifier: Operating System :: OS Independent
Requires-Python: >=3.8
License-File: LICENSE
Requires-Dist: streamlit
Requires-Dist: openmc-source-plotter >=0.6.2
Requires-Dist: dagmc-geometry-slice-plotter >=0.3.1
Requires-Dist: openmc-geometry-plot >=0.4.3
Requires-Dist: regular-mesh-plotter >=0.5.3
Requires-Dist: openmc-depletion-plotter >=0.3.1
Requires-Dist: openmc-cylindrical-mesh-plotter >=0.1.2
Provides-Extra: tests
Requires-Dist: pytest ; extra == 'tests'
Requires-Dist: requests ; extra == 'tests'
